pybakong/__init__.py
pybakong/client.py
pybakong/exceptions.py
pybakong-0.1.0.dist-info/METADATA
pybakong-0.1.0.dist-info/WHEEL
pybakong-0.1.0.dist-info/top_level.txt
pybakong-0.1.0.dist-info/RECORD
