Metadata-Version: 2.4
Name: pybakong
Version: 0.1.0
Summary: Python SDK for Cambodia Bakong Open API
Author-email: Your Name <you@example.com>
Requires-Python: >=3.7
Requires-Dist: requests
